MANIFEST.in
README.md
setup.py
pyom/__init__.py
pyom/container.py
pyom/exceptions.py
pyom/gateway.py
pyom/immutable_object.py
pyom/mapper.py
pyom/relation.py
pyom/repository.py
pyom.egg-info/PKG-INFO
pyom.egg-info/SOURCES.txt
pyom.egg-info/dependency_links.txt
pyom.egg-info/top_level.txt
pyom/plugins/__init__.py
pyom/plugins/apply_gateway.py
pyom/plugins/restli_pagination.py