Metadata-Version: 2.1
Name: pyom
Version: 0.0.2
Summary: Python Object Mapper
Home-page: https://github.com/pyom/pyom
Author: Python Object Mapper
Author-email: maxim@derbin.io
License: MIT
Platform: UNKNOWN
Classifier: License :: OSI Approved :: MIT License
Classifier: Programming Language :: Python
Classifier: Programming Language :: Python :: 3
